wikiweb/__init__.py
wikiweb/cli.py
wikiweb/wikiweb.py
wikiweb-0.1.6.dist-info/DESCRIPTION.rst
wikiweb-0.1.6.dist-info/METADATA
wikiweb-0.1.6.dist-info/RECORD
wikiweb-0.1.6.dist-info/WHEEL
wikiweb-0.1.6.dist-info/entry_points.txt
wikiweb-0.1.6.dist-info/metadata.json
wikiweb-0.1.6.dist-info/top_level.txt
